atsphinx/highlightjs/__init__.py
atsphinx/highlightjs/_static/highlight.css
atsphinx/highlightjs/_static/highlight.js
atsphinx_highlightjs-0.1.1.dist-info/LICENSE
atsphinx_highlightjs-0.1.1.dist-info/WHEEL
atsphinx_highlightjs-0.1.1.dist-info/METADATA
atsphinx_highlightjs-0.1.1.dist-info/RECORD
