Metadata-Version: 2.1
Name: atsphinx-highlightjs
Version: 0.1.1
Summary: Override code-block output for highlight.js.
Author-email: Kazuya Takei <myself@attakei.net>
Classifier: Development Status :: 3 - Alpha
Classifier: Framework :: Sphinx
Classifier: Framework :: Sphinx :: Extension
Classifier: Intended Audience :: Developers
Classifier: License :: OSI Approved :: Apache Software License
Classifier: Programming Language :: Python :: 3.8
Classifier: Programming Language :: Python :: 3.9
Classifier: Programming Language :: Python :: 3.10
Classifier: Programming Language :: Python :: 3.11
Classifier: Programming Language :: Python :: 3.12
Classifier: Topic :: Documentation :: Sphinx
Requires-Dist: sphinx
Requires-Dist: pytest ==7.* ; extra == "test"
Project-URL: Home, https://github.com/atsphinx/highlightjs
Provides-Extra: test
